melodine/__init__.py
melodine/configs.py
melodine/innertube.py
melodine/models/__init__.py
melodine/models/base/__init__.py
melodine/models/base/album.py
melodine/models/base/artist.py
melodine/models/base/playlist.py
melodine/models/base/track.py
melodine/models/spotify/__init__.py
melodine/models/spotify/_search.py
melodine/models/spotify/album.py
melodine/models/spotify/artist.py
melodine/models/spotify/client.py
melodine/models/spotify/device.py
melodine/models/spotify/episode.py
melodine/models/spotify/player.py
melodine/models/spotify/playlist.py
melodine/models/spotify/show.py
melodine/models/spotify/track.py
melodine/models/spotify/user.py
melodine/models/youtube/__init__.py
melodine/models/youtube/_search.py
melodine/models/ytmusic/__init__.py
melodine/models/ytmusic/_search.py
melodine/models/ytmusic/album.py
melodine/models/ytmusic/artist.py
melodine/models/ytmusic/playlist.py
melodine/models/ytmusic/track.py
melodine/models/ytmusic/user.py
melodine/models/ytmusic/video.py
melodine/utils.py
melodine-0.2.8.dist-info/WHEEL
melodine-0.2.8.dist-info/METADATA
melodine-0.2.8.dist-info/RECORD
