Metadata-Version: 2.1
Name: melodine
Version: 0.2.8
Summary: cohesive models for seamlessly interacting with the Spotify and YouTube Music APIs
License: MIT
Author: addyett
Author-email: g.aditya2048@gmail.com
Requires-Python: >=3.8,<4.0
Classifier: License :: OSI Approved :: MIT License
Classifier: Programming Language :: Python :: 3
Classifier: Programming Language :: Python :: 3.8
Classifier: Programming Language :: Python :: 3.9
Classifier: Programming Language :: Python :: 3.10
Classifier: Programming Language :: Python :: 3.11
Requires-Dist: appdirs (>=1.4.4,<2.0.0)
Requires-Dist: python-youtube (>=0.8.3,<0.9.0)
Requires-Dist: requests (>=2.28.1,<3.0.0)
Requires-Dist: spotipy (>=2.21.0,<3.0.0)
Requires-Dist: youtube_dl (>=2021.12.17,<2022.0.0)
Requires-Dist: ytmusicapi (>=0.24.0,<0.25.0)
